django_json_editor_field/.gitignore
django_json_editor_field/__init__.py
django_json_editor_field/fields.py
django_json_editor_field/widgets.py
django_json_editor_field/static/css/jsonwidget.css
django_json_editor_field/static/js/jsonwidget.js
django_json_editor_field/templates/widgets/json_editor_widget.html
django_json_editor_field-0.4.2.dist-info/METADATA
django_json_editor_field-0.4.2.dist-info/WHEEL
django_json_editor_field-0.4.2.dist-info/RECORD
