Metadata-Version: 2.4
Name: django-json-editor-field
Version: 0.4.2
Summary: JSON Editor support for Django JSON Fields
Author-email: Birger Schacht <birger.schacht@oeaw.ac.at>
License-Expression: MIT
Requires-Python: >=3.11
Requires-Dist: django>=4
Requires-Dist: jsonschema>=4.23.0
